youtube_search_mcp/__init__.py
youtube_search_mcp/server.py
youtube_search_mcp/core/__init__.py
youtube_search_mcp/core/config.py
youtube_search_mcp/core/exceptions.py
youtube_search_mcp/core/interfaces.py
youtube_search_mcp/download/__init__.py
youtube_search_mcp/download/progress_tracker.py
youtube_search_mcp/download/quality_presets.py
youtube_search_mcp/download/ytdlp_downloader.py
youtube_search_mcp/formatters/__init__.py
youtube_search_mcp/formatters/json_formatter.py
youtube_search_mcp/formatters/markdown_formatter.py
youtube_search_mcp/models/__init__.py
youtube_search_mcp/models/download_params.py
youtube_search_mcp/models/playlist.py
youtube_search_mcp/models/search_params.py
youtube_search_mcp/models/video.py
youtube_search_mcp/search/__init__.py
youtube_search_mcp/search/parsers.py
youtube_search_mcp/search/retry_decorator.py
youtube_search_mcp/search/ytdlp_provider.py
youtube_search_mcp/tools/README.md
youtube_search_mcp/tools/__init__.py
youtube_search_mcp/tools/dependencies.py
youtube_search_mcp/tools/download_tools.py
youtube_search_mcp/tools/playlist_tools.py
youtube_search_mcp/tools/resources.py
youtube_search_mcp/tools/search_tools.py
youtube_search_mcp/tools/utility_tools.py
youtube_search_mcp/utils/__init__.py
youtube_search_mcp/utils/file_utils.py
youtube_search_mcp/utils/logger.py
youtube_search_mcp/utils/validators.py
youtube_search_mcp-1.0.3.dist-info/METADATA
youtube_search_mcp-1.0.3.dist-info/WHEEL
youtube_search_mcp-1.0.3.dist-info/entry_points.txt
youtube_search_mcp-1.0.3.dist-info/licenses/LICENSE
youtube_search_mcp-1.0.3.dist-info/RECORD
