Metadata-Version: 2.4
Name: youtube-search-mcp
Version: 1.0.3
Summary: YouTube search and download MCP server using yt-dlp and FastMCP 2.0
Project-URL: Homepage, https://github.com/easyhak/youtube-search-mcp
Project-URL: Documentation, https://github.com/easyhak/youtube-search-mcp#readme
Project-URL: Repository, https://github.com/easyhak/youtube-search-mcp
Project-URL: Issues, https://github.com/easyhak/youtube-search-mcp/issues
Author-email: JIHAK LEE <zhzhk17@gmail.com>
License: MIT
License-File: LICENSE
Keywords: download,fastmcp,mcp,model-context-protocol,search,youtube,yt-dlp
Classifier: Development Status :: 4 - Beta
Classifier: Intended Audience :: Developers
Classifier: License :: OSI Approved :: MIT License
Classifier: Programming Language :: Python :: 3
Classifier: Programming Language :: Python :: 3.10
Classifier: Programming Language :: Python :: 3.11
Classifier: Programming Language :: Python :: 3.12
Classifier: Topic :: Internet :: WWW/HTTP
Classifier: Topic :: Multimedia :: Video
Classifier: Topic :: Software Development :: Libraries :: Python Modules
Requires-Python: >=3.10
Requires-Dist: fastmcp>=2.0.0
Requires-Dist: pydantic-settings>=2.0.0
Requires-Dist: pydantic>=2.0.0
Requires-Dist: yt-dlp>=2024.1.0
Provides-Extra: dev
Requires-Dist: black>=23.0.0; extra == 'dev'
Requires-Dist: mypy>=1.0.0; extra == 'dev'
Requires-Dist: pytest-asyncio>=0.21.0; extra == 'dev'
Requires-Dist: pytest-cov>=4.0.0; extra == 'dev'
Requires-Dist: pytest-mock>=3.10.0; extra == 'dev'
Requires-Dist: pytest>=7.0.0; extra == 'dev'
Requires-Dist: ruff>=0.1.0; extra == 'dev'
